ashes.py
ashes-24.0.0.data/scripts/ashes.py
ashes-24.0.0.dist-info/LICENSE
ashes-24.0.0.dist-info/METADATA
ashes-24.0.0.dist-info/WHEEL
ashes-24.0.0.dist-info/entry_points.txt
ashes-24.0.0.dist-info/top_level.txt
ashes-24.0.0.dist-info/RECORD
